{"127":"yüz yirmi yedi","71":"yetmiş bir","882":"sekiz yüz seksen iki","560":"beş yüz altmış","898":"sekiz yüz doksan sekiz","798":"yedi yüz doksan sekiz","512":"beş yüz on iki","463":"dört yüz altmış üç","458":"dört yüz elli sekiz","517":"beş yüz sevik","451":"dört yüz elli bir","454":"dört yüz elli dört","722":"yedi yüz yirmi iki","634":"altı yüz otuz dört","578":"beş yüz yetmiş sekiz","695":"altı yüz doksan beş","978":"dokuz yüz yetmiş sekiz","728":"yedi yüz yirmi sekiz","742":"yedi yüz kırk iki","378":"üç yüz yetmiş sekiz","325":"üç yüz yirmi beş","29":"yirmi dokuz","889":"sekiz yüz seksen dokuz","350":"üç yüz elli","540":"beş yüz kırk","58":"elli sekiz","211":"iki yüz on bir","153":"yüz elli üç","684":"altı yüz seksen dört","861":"sekiz yüz altmış bir","337":"üç yüz otuz yedi","101":"yüz bir","340":"üç yüz kırk","76":"yetmiş altı","311":"üç yüz on bir","982":"dokuz yüz seksen iki","571":"beş yüz yetmiş bir","825":"sekiz yüz yirmi beş","389":"üç yüz seksen dokuz","917":"dokuz yüz sevik","495":"dört yüz doksan beş","966":"dokuz yüz altmış altı","992":"dokuz yüz doksan iki","236":"iki yüz otuz altı","758":"yedi yüz elli sekiz","218":"iki yüz on sekiz","706":"yedi yüz altı","14":"on dört","834":"sekiz yüz otuz dört","285":"iki yüz seksen beş","234":"iki yüz otuz dört","594":"beş yüz doksan dört","96":"doksan altı","486":"dört yüz seksen altı","160":"yüz altmış","569":"beş yüz altmış dokuz","8":"sekiz","98":"doksan sekiz","43":"kırk üç","686":"altı yüz seksen altı","391":"üç yüz doksan bir","943":"dokuz yüz kırk üç","288":"iki yüz seksen sekiz","193":"yüz doksan üç","119":"yüz on dokuz","180":"yüz seksen","586":"beş yüz seksen altı","410":"dört yüz on","246":"iki yüz kırk altı","999":"999","690":"altı yüz doksan","61":"altmışbir","430":"dört yüz otuz","447":"dört yüz kırk yedi","536":"beş yüz otuz altı","415":"dört yüz on beş","189":"yüz seksen dokuz","480":"dört yüz seksen","107":"yüz yedi","438":"dört yüz otuz sekiz","87":"seksen yedi","444":"dört yüz kırk dört","508":"beş yüz sekiz","953":"dokuz yüz elli üç","221":"iki yüz yirmi bir","39":"otuz dokuz","558":"beş yüz elli sekiz","12":"on iki","417":"dört yüz on yedi","784":"yedi yüz seksen dört","260":"iki yüz altmış","573":"beş yüz yetmiş üç","762":"yedi yüz altmış iki","638":"altı yüz otuz sekiz","734":"yedi yüz otuz dört","875":"sekiz yüz yetmiş beş","1":"bir","116":"yüz on altı","136":"yüz otuz altı","506":"beş yüz altı","144":"yüz kırk dört","661":"altı yüz altmış bir","381":"üç yüz seksen bir","581":"beş yüz seksen bir","308":"üç yüz sekiz","906":"dokuz yüz altı","177":"yüz yetmiş yedi","678":"altı yüz yetmiş sekiz","373":"üç yüz yetmiş üç","773":"yedi yüz yetmiş üç","205":"iki yüz beş","22":"yirmi iki","927":"dokuz yüz yirmi yedi","301":"üç yüz","51":"elli bir","456":"dört yüz elli altı","874":"sekiz yüz yetmiş dört","652":"altı yüz elli iki","975":"dokuz yüz yetmiş beş","493":"dört yüz doksan üç","796":"yedi yüz doksan altı","366":"üç yüz altmış altı","844":"sekiz yüz kırk dört","272":"iki yüz yetmiş iki","775":"yedi yüz yetmiş beş","919":"dokuz yüz on dokuz","400":"dort yuz","534":"beş yüz otuz dört","746":"yedi yüz kırk altı","20":"yirmi","744":"yedi yüz kırk dört","888":"sekiz yüz seksen sekiz","633":"altı yüz otuz üç","151":"yüz elli bir","468":"dört yüz altmış sekiz","287":"iki yüz seksen yedi","700":"yedi yüz","78":"yetmiş sekiz","475":"dört yüz yetmiş beş","990":"dokuz yüz doksan","294":"iki yüz doksan dört","413":"dört yüz on üç","932":"dokuz yüz otuz iki","349":"üç yüz kırk dokuz","764":"yedi yüz altmış dört","515":"beşyüz onbeş","138":"yüz otuz sekiz","606":"altı yüz altı","137":"yüz otuz yedi","724":"yedi yüz yirmi dört","432":"dört yüz otuz iki","666":"altı yüz altmış altı","519":"beş yüz on dokuz","860":"sekiz yüz altmış","17":"on yedi","708":"yedi yüz sekiz","110":"yüzon","333":"üç yüz otuz üç","710":"yedi yüz on","323":"üç yüz yirmi üç","856":"sekiz yüz elli altı","112":"yüz on iki","191":"yüz doksan bir","545":"beş yüz kırk beş","187":"yüz seksen yedi","588":"beş yüz seksen sekiz","646":"altı yüz kırk altı","756":"yedi yüz elli altı","446":"dört yüz kırk altı","262":"iki yüz altmış iki","212":"iki yüz on iki","542":"beş yüz kırk iki","961":"dokuz yüz altmış bir","810":"sekiz yüz on","574":"beş yüz yetmiş dört","170":"yüz yetmiş","33":"otuz üç","660":"altı yüz altmış","7":"yedi","227":"iki yüz yirmi yedi","26":"yirmi altı","977":"dokuz yüz yetmiş yedi","526":"beş yüz yirmi altı","566":"beş yüz altmış altı","806":"sekiz yüz altı","264":"iki yüz altmış dört","255":"iki yüz elli beş","359":"üç yüz elli dokuz","182":"yüz seksen iki","108":"yüz sekiz","604":"altı yüz dört","556":"beş yüz elli altı","717":"yedi yüz seventeen","232":"iki yüz otuz iki","477":"dört yüz yetmiş yedi","815":"sekiz yüz on beş","671":"altı yüz yetmiş bir","225":"iki yüz yirmi beş","330":"üç yüz otuz","207":"iki yüz yedi","142":"yüz kırk iki","167":"yüz altmış yedi","48":"kırk sekiz","360":"üç yüz altmış","692":"altı yüz doksan iki","663":"altı yüz altmış üç","854":"sekiz yüz elli dört","969":"dokuz yüz altmış dokuz","510":"beş yüz on","766":"yedi yüz altmış altı","393":"üç yüz doksan üç","449":"dört yüz kırk dokuz","658":"altı yüz elli sekiz","274":"iki yüz yetmiş dört","549":"beş yüz kırk dokuz","877":"sekiz yüz yetmiş yedi","659":"altı yüz elli dokuz","682":"altı yüz seksen iki","353":"üç yüz elli üç","375":"üç yüz yetmiş beş","984":"dokuz yüz seksen dört","946":"dokuz yüz kırk altı","788":"yedi yüz seksen sekiz","128":"yüz yirmi sekiz","303":"üç yüz üç","250":"iki yüz elli","614":"altı yüz on dört","501":"beş yüz bir","278":"iki yüz yetmiş sekiz","490":"dört yüz doksan","130":"yüz otuz","155":"yüz elli beş","53":"elli üç","387":"üç yüz seksen yedi","626":"altı yüz yirmi altı","941":"dokuz yüz kırk bir","461":"dört yüz altmış bir","583":"beş yüz seksen üç","257":"iki yüz elli yedi","951":"dokuz yüz elli bir","782":"yedi yüz seksen iki","85":"seksen beş","809":"sekiz yüz dokuz","425":"dört yüz yirmi beş","591":"beş yüz doksan bir","832":"sekiz yüz otuz iki","736":"yedi yüz otuz altı","539":"beş yüz otuz dokuz","781":"yedi yüz seksen bir","828":"sekiz yüz yirmi sekiz","276":"iki yüz yetmiş altı","102":"yüziki","520":"beş yüz yirmi","532":"beş yüz otuz iki","55":"elli beş","259":"iki yüz elli dokuz","57":"elli yedi","424":"dört yüz yirmi dört","872":"sekiz yüz yetmiş iki","163":"yüz altmış üç","395":"üç yüz doksan beş","89":"seksen dokuz","175":"yüz yetmiş beş","584":"beş yüz seksen dört","988":"dokuz yüz seksen sekiz","35":"otuzbeş","347":"üç yüz kırk yedi","665":"altı yüz altmış beş","434":"dört yüz otuz dört","865":"sekiz yüz altmış beş","904":"dokuz yüz dört","930":"dokuz yüz otuz","442":"dört yüz kırk iki","649":"altı yüz kırk dokuz","689":"altı yüz seksen dokuz","886":"sekiz yüz seksen altı","642":"altı yüz kırk iki","648":"altı yüz kırk sekiz","198":"yüz doksan sekiz","727":"yedi yüz yirmi yedi","939":"dokuz yüz otuz dokuz","320":"üç yüz yirmi","913":"dokuz yüz on üç","811":"sekiz yüz on bir","361":"üç yüz altmış bir","249":"iki yüz kırk dokuz","202":"iki yüz iki","465":"dört yüz altmış beş","184":"yüz seksen dört","819":"sekiz yüz on dokuz","776":"yedi yüz yetmiş altı","894":"sekiz yüz doksan dört","858":"sekiz yüz elli sekiz","140":"yüzkırk","181":"yüz seksen bir","412":"dört yüz on iki","954":"dokuz yüz elli dört","385":"üç yüz seksen beş","307":"üç yüz yedi","801":"sekiz yüz bir","985":"dokuz yüz seksen beş","971":"dokuz yüz yetmiş bir","830":"sekiz yüz otuz","154":"yüz elli dört","754":"yedi yüz elli dört","847":"sekiz yüz kırk yedi","479":"dört yüz yetmiş dokuz","704":"yedi yüz dört","326":"üç yüz yirmi altı","681":"altı yüz seksen bir","619":"619","335":"üç yüz otuz beş","5":"beş","698":"altı yüz doksan sekiz","621":"altı yüz yirmi bir","524":"beş yüz yirmi dört","554":"beş yüz elli dört","552":"beş yüz elli iki","598":"beş yüz doksan sekiz","780":"yedi yüz seksen","240":"iki yüz kırk","74":"yetmiş dört","890":"sekiz yüz doksan","440":"dört yüz kırk","230":"iki yüz otuz","299":"iki yüz doksan dokuz","115":"yüz on beş","377":"üç yüz yetmiş yedi","922":"dokuz yüz yirmi iki","602":"altı yüz iki","841":"sekiz yüz kırk bir","612":"altı yüz on iki","936":"dokuz yüz otuz altı","91":"doksan bir","467":"dört yüz altmış yedi","701":"yedi yüz bir","474":"dört yüz yetmiş dört","481":"dört yüz seksen bir","867":"sekiz yüz altmış yedi","214":"iki yüz on dört","564":"beş yüz altmış dört","817":"sekiz yüz on yedi","563":"beş yüz altmış üç","731":"yedi yüz otuz bir","657":"altı yüz elli yedi","229":"iki yüz yirmi dokuz","768":"yedi yüz altmış sekiz","503":"beş yüz üç","673":"altı yüz yetmiş üç","68":"altmış sekiz","315":"üç yüz on beş","338":"üç yüz otuz sekiz","576":"beş yüz yetmiş altı","761":"yedi yüz altmış bir","222":"iki yüz yirmi iki","25":"yirmi beş","738":"yedi yüz otuz sekiz","484":"dört yüz seksen dört","305":"üç yüz beş","928":"dokuz yüz yirmi sekiz","544":"beş yüz kırk dört","623":"altı yüz yirmi üç","217":"iki yüz sevim","328":"üç yüz yirmi sekiz","239":"iki yüz otuz dokuz","122":"yüz yirmi iki","878":"sekiz yüz yetmiş sekiz","281":"iki yüz seksen bir","269":"iki yüz altmış dokuz","158":"yüz elli sekiz","628":"altı yüz yirmi sekiz","363":"üç yüz altmış üç","46":"kırk altı","733":"yedi yüz otuz üç","997":"dokuz yüz doksan yedi","36":"otuz altı","630":"altı yüz otuz","472":"dört yüz yetmiş iki","748":"yedi yüz kırk sekiz","317":"üç yüz on yedi","608":"altı yüz sekiz","132":"yüz otuz iki","711":"yedi yüz on bir","892":"sekiz yüz doksan iki","546":"beş yüz kırk altı","537":"beş yüz otuz yedi","125":"yüz yirmi beş","522":"beş yüz yirmi iki","44":"kırkdört","667":"altı yüz altmış yedi","741":"yedi yüz kırk bir","998":"dokuz yüz doksan sekiz","714":"yedi yüz on dört","313":"üç yüz on üç","529":"beş yüz yirmi dokuz","987":"dokuz yüz seksen yedi","397":"üç yüz doksan yedi","908":"dokuz yüz sekiz","459":"dört yüz elli dokuz","284":"iki yüz seksen dört","823":"sekiz yüz yirmi üç","903":"dokuz yüz üç","247":"iki yüz kırk yedi","289":"iki yüz seksen dokuz","165":"yüz altmış beş","729":"yedi yüz yirmi dokuz","771":"yedi yüz yetmiş bir","2":"iki","808":"sekiz yüz sekiz","401":"dört yüz bir","845":"sekiz yüz kırk beş","186":"yüz seksen altı","147":"yüz kırk yedi","973":"dokuz yüz yetmiş üç","915":"dokuz yüz on beş","319":"üç yüz on dokuz","404":"dört yüz dört","735":"yedi yüz otuz beş","516":"beş yüz on altı","974":"dokuz yüz yetmiş dört","702":"yedi yüz iki","344":"üç yüz kırk dört","636":"altı yüz otuz altı","561":"beş yüz altmış bir","209":"iki yüz dokuz","357":"üç yüz elli yedi","117":"yüz on yedi","455":"dört yüz elli beş","80":"seksen","600":"altı yüz","336":"üç yüz otuz altı","457":"dört yüz elli yedi","821":"sekiz yüz yirmi bir","383":"üç yüz seksen üç","696":"altı yüz doksan altı","963":"dokuz yüz altmış üç","297":"iki yüz doksan yedi","92":"doksan iki","980":"dokuz yüz seksen","10":"on","550":"beş yüz elli","505":"beş yüz beş","670":"altı yüz yetmiş","958":"dokuz yüz elli sekiz","419":"dört yüz on dokuz","995":"dokuz yüz doksan beş","837":"sekiz yüz otuz yedi","290":"iki yüz doksan","149":"yüz kırk dokuz","592":"beş yüz doksan iki","625":"altı yüz yirmi beş","210":"iki yüz on","712":"yedi yüz on iki","406":"dört yüz altı","173":"yüz yetmiş üç","530":"beş yüz otuz","66":"altmış altı","19":"on dokuz","365":"üç yüz altmış beş","763":"yedi yüz altmış üç","470":"dört yüz yetmiş","793":"yedi yüz doksan üç","570":"beş yüz yetmiş","654":"altı yüz elli dört","252":"iki yüz elli iki","883":"sekiz yüz seksen üç","283":"iki yüz seksen üç","156":"yüz elli altı","655":"altı yüz elli beş","59":"elli dokuz","421":"dört yüz yirmi bir","271":"iki yüz yetmiş bir","491":"dört yüz doksan bir","864":"sekiz yüz altmış dört","219":"iki yüz on dokuz","13":"on üç","799":"yedi yüz doksan dokuz","105":"yüz beş","925":"dokuz yüz yirmi beş","840":"sekiz yüz kırk","390":"üç yüz doksan","597":"beş yüz doksan yedi","111":"yüz on bir","38":"otuz sekiz","408":"dört yüz sekiz","196":"yüz doksan altı","945":"dokuz yüz kırk beş","242":"iki yüz kırk iki","559":"beş yüz elli dokuz","32":"otuz iki","206":"iki yüz altı","118":"yüz on sekiz","443":"dört yüz kırk üç","959":"dokuz yüz elli dokuz","358":"üç yüz elli sekiz","331":"üç yüz otuz bir","737":"yedi yüz otuz yedi","580":"beş yüz seksen","767":"yedi yüz altmış yedi","805":"sekiz yüz beş","84":"seksen dört","437":"dört yüz otuz yedi","194":"yüz doksan dört","220":"iki yüz yirmi","846":"sekiz yüz kırk altı","31":"otuz bir","934":"dokuz yüz otuz dört","948":"dokuz yüz kırk sekiz","572":"beş yüz yetmiş iki","968":"dokuz yüz altmış sekiz","675":"altı yüz yetmiş beş","226":"iki yüz yirmi altı","15":"on beş","431":"dört yüz otuz bir","527":"beş yüz yirmi yedi","382":"üç yüz seksen iki","62":"altmış iki","833":"sekiz yüz otuz üç","139":"yüz otuz dokuz","129":"yüz yirmi dokuz","926":"dokuz yüz yirmi altı","548":"beş yüz kırk sekiz","859":"sekiz yüz elli dokuz","739":"yedi yüz otuz dokuz","876":"sekiz yüz yetmiş altı","662":"altı yüz altmış iki","418":"dört yüz on sekiz","933":"dokuz yüz otuz üç","783":"yedi yüz seksen üç","168":"yüz altmış sekiz","135":"135","348":"üç yüz kırk sekiz","145":"yüz kırk beş","789":"yedi yüz seksen dokuz","49":"kırk dokuz","178":"yüz yetmiş sekiz","772":"yedi yüz yetmiş iki","124":"yüz yirmi dört","993":"dokuz yüz doksan üç","627":"altı yüz yirmi yedi","715":"yedi yüz on beş","0":"sıfır","23":"yirmi üç","364":"üç yüz altmış dört","388":"üç yüz seksen sekiz","653":"altı yüz elli üç","950":"dokuz yüz elli","509":"beş yüz dokuz","976":"dokuz yüz yetmiş altı","367":"üç yüz altmış yedi","716":"yedi yüz on altı","940":"dokuz yüz kırk","485":"dört yüz seksen beş","778":"yedi yüz yetmiş sekiz","685":"altı yüz seksen beş","743":"yedi yüz kırk üç","21":"yirmi bir","523":"beş yüz yirmi üç","720":"yedi yüz yirmi","460":"dört yüz altmış","324":"üç yüz yirmi dört","453":"dört yüz elli üç","723":"yedi yüz yirmi üç","244":"iki yüz kırk dört","637":"altı yüz otuz yedi","351":"üç yüz elli bir","595":"beş yüz doksan beş","488":"dört yüz seksen sekiz","752":"yedi yüz elli iki","835":"sekiz yüz otuz beş","379":"üç yüz yetmiş dokuz","901":"dokuz yüz bir","113":"yüz on üç","152":"yüz elli iki","342":"üç yüz kırk iki","452":"dört yüz elli iki","862":"sekiz yüz altmış iki","295":"iki yüz doksan beş","579":"beş yüz yetmiş dokuz","341":"üç yüz kırk bir","535":"beş yüz otuz beş","77":"yetmiş yedi","683":"altı yüz seksen üç","541":"beş yüz kırk bir","64":"altmış dört","881":"sekizyüz seksenbir","765":"yedi yüz altmış beş","897":"sekiz yüz doksan yedi","312":"üç yüz on iki","45":"kırkbeş","405":"dört yüz beş","507":"beş yüz yedi","237":"iki yüz otuz yedi","370":"üç yüz yetmiş","309":"üç yüz dokuz","567":"beş yüz altmış yedi","416":"dört yüz on altı","914":"dokuz yüz on dört","380":"üç yüz seksen","100":"yüz","965":"dokuz yüz altmış beş","300":"üç yüz","824":"sekiz yüz yirmi dört","286":"iki yüz seksen altı","120":"yüz yirmi","800":"sekiz yüz","254":"iki yüz elli dört","392":"üç yüz doksan iki","496":"dört yüz doksan altı","605":"altı yüz beş","607":"altı yüz yedi","813":"sekiz yüz on üç","42":"kırk iki","644":"altı yüz kırk dört","759":"yedi yüz elli dokuz","851":"sekiz yüz elli bir","399":"üç yüz doksan dokuz","235":"iki yuz otuz bes","694":"altı yüz doksan dört","436":"dört yüz otuz altı","213":"iki yüz on üç","94":"doksan dört","816":"sekiz yüz on altı","568":"beş yüz altmış sekiz","296":"iki yüz doksan altı","265":"iki yüz altmış beş","791":"yedi yüz doksan bir","171":"yüz yetmiş bir","916":"dokuz yüz on altı","386":"üç yüz seksen altı","445":"dört yüz kırk beş","200":"iki yüz","329":"üç yüz yirmi dokuz","525":"beş yüz yirmi beş","787":"yedi yüz seksen yedi","27":"yirmi yedi","161":"yüz altmış bir","582":"beş yüz seksen iki","109":"yüz dokuz","557":"beş yüz elli yedi","718":"yedi yüz on sekiz","441":"dört yüz kırk bir","868":"sekiz yüz altmış sekiz","672":"altı yüz yetmiş iki","769":"yedi yüz altmış dokuz","983":"dokuz yüz seksen üç","275":"iki yüz yetmiş beş","803":"sekiz yüz üç","197":"yüz doksan yedi","853":"sekiz yüz elli üç","751":"yedi yüz elli bir","60":"altmış","691":"altı yüz doksan bir","346":"üç yüz kırk altı","911":"dokuz yüz on bir","427":"dört yüz yirmi yedi","677":"altı yüz yetmiş yedi","907":"dokuz yüz yedi","82":"seksen iki","650":"altı yüz elli","590":"beş yüz doksan","895":"sekiz yüz doksan beş","69":"altmışdokuz","664":"altı yüz altmış dört","224":"iki yüz yirmi dört","79":"yetmiş dokuz","617":"altı yüz on yedi","352":"üç yüz elli iki","126":"yüz yirmi altı","251":"iki yüz elli bir","426":"dört yüz yirmi altı","996":"dokuz yüz doksan altı","369":"üç yüz altmış dokuz","279":"iki yüz yetmiş dokuz","651":"altı yüz elli bir","176":"yüz yetmiş altı","956":"dokuz yüz elli altı","483":"dört yüz seksen üç","498":"dört yüz doksan sekiz","629":"altı yüz yirmi dokuz","947":"dokuz yüz kırk yedi","256":"iki yüz elli altı","372":"üç yüz yetmiş iki","920":"dokuz yüz yirmi","428":"dört yüz yirmi sekiz","887":"sekiz yüz seksen yedi","99":"doksan dokuz","72":"yetmiş iki","869":"sekiz yüz altmış dokuz","500":"beş yüz","790":"yedi yüz doksan","533":"beş yüz otuz üç","918":"dokuz yüz on sekiz","414":"dört yüz on dört","462":"dört yüz altmış iki","843":"sekiz yüz kırk üç","263":"iki yüz altmış üç","632":"altı yüz otuz iki","991":"dokuz yüz doksan bir","394":"üç yüz doksan dört","514":"beş yüz on dört","610":"altı yüz on","931":"dokuz yüz otuz bir","725":"yedi yüz yirmi beş","513":"beş yüz on üç","615":"altı yüz on beş","50":"elli","476":"dört yüz yetmiş altı","797":"yedi yüz doksan yedi","293":"iki yüz doksan üç","967":"dokuz yüz altmış yedi","322":"üç yüz yirmi iki","645":"altı yüz kırk beş","469":"dört yüz altmış dokuz","635":"altı yüz otuz beş","575":"beş yüz yetmiş beş","979":"dokuz yüz yetmiş dokuz","709":"yedi yüz dokuz","28":"yirmi sekiz","310":"üç yüz on","40":"kırk","192":"yüz doksan iki","589":"beş yüz seksen dokuz","215":"iki yüz on beş","699":"altı yüz doksan dokuz","687":"altı yüz seksen yedi","960":"dokuz yüz altmış","818":"sekiz yüz on sekiz","150":"yüz elli","245":"iki yüz kırk beş","267":"iki yüz altmış yedi","543":"beş yüz kırk üç","826":"sekiz yüz yirmi altı","354":"üç yüz elli dört","757":"yedi yüz elli yedi","332":"üç yüz otuz iki","9":"dokuz","34":"otuz dört","745":"yedi yüz kırk beş","603":"altı yüz üç","90":"doksan","565":"beş yüz altmış beş","620":"altı yüz yirmi","850":"sekiz yüz elli","937":"dokuz yüz otuz yedi","891":"sekiz yüz doksan bir","16":"on altı","730":"yedi yüz otuz","921":"dokuz yüz yirmi bir","233":"iki yüz otuz üç","368":"üç yüz altmış sekiz","316":"üç yüz on altı","994":"dokuz yüz doksan dört","611":"altı yüz on bir","849":"sekiz yüz kırk dokuz","11":"on bir","492":"dört yüz doksan iki","208":"iki yüz sekiz","842":"sekiz yüz kırk iki","511":"beş yüz on bir","93":"doksan üç","899":"sekiz yüz dokuz","292":"iki yüz doksan iki","291":"iki yüz doksan bir","374":"üç yüz yetmiş dört","199":"yüz doksan dokuz","114":"yüz on dört","429":"dört yüz yirmi dokuz","73":"yetmiş üç","409":"dört yüz dokuz","67":"altmış yedi","812":"sekiz yüz on iki","795":"yedi yüz doksan beş","241":"iki yüz kırk bir","489":"dört yüz seksen dokuz","794":"yedi yüz doksan dört","585":"beş yüz seksen beş","327":"üç yüz yirmi yedi","944":"dokuz yüz kırk dört","674":"altı yüz yetmiş dört","732":"yedi yüz otuz iki","957":"dokuz yüz elli yedi","280":"iki yüz seksen","273":"iki yüz yetmiş üç","471":"dört yüz yetmiş bir","622":"altı yüz yirmi iki","970":"dokuz yüz yetmiş","24":"yirmidört","104":"yüzdört","131":"yüz otuz bir","502":"beş yüz iki","314":"üç yüz on dört","355":"üç yüz elli beş","159":"yüz elli dokuz","553":"beş yüz elli üç","747":"yedi yüz kırk yedi","555":"beş yüz elli beş","47":"kırk yedi","37":"otuz yedi","855":"sekiz yüz elli beş","270":"iki yüz yetmiş","195":"yüz doksan beş","538":"beş yüz otuz sekiz","679":"altı yüz yetmiş dokuz","680":"altı yüz seksen","831":"sekiz yüz otuz bir","521":"beş yüz yirmi bir","162":"yüz altmış iki","880":"sekiz yüz seksen","433":"dört yüz otuz üç","647":"altı yüz kırk yedi","334":"üç yüz otuz dört","986":"dokuz yüz seksen altı","786":"yedi yüz seksen altı","740":"yedi yüz kırk","103":"yüz üç","201":"iki yüz bir","871":"sekiz yüz yetmiş bir","423":"dört yüz yirmi üç","719":"yedi yüz on dokuz","902":"dokuz yüz iki","827":"sekiz yüz yirmi yedi","266":"iki yüz altmış altı","820":"sekiz yüz yirmi","174":"yüz yetmiş dört","422":"dört yüz yirmi iki","905":"dokuz yüz beş","97":"doksan yedi","41":"kırk bir","668":"altı yüz altmış sekiz","52":"elli iki","688":"altı yüz seksen sekiz","750":"yedi yüz elli","302":"üç yüz iki","774":"yedi yüz yetmiş dört","866":"sekiz yüz altı altı","910":"dokuz yüz on","693":"altı yüz doksan üç","770":"yedi yüz yetmiş","593":"beş yüz doksan üç","188":"yüz sekiz sekiz","402":"dört yüz iki","641":"altı yüz kırk bir","893":"sekiz yüz doksan üç","838":"sekiz yüz otuz sekiz","616":"altı yüz on altı","640":"altı yüz kırk","870":"sekiz yüz yetmiş","804":"sekiz yüz dört","83":"seksen üç","896":"sekiz yüz doksan altı","962":"dokuz yüz altmış iki","755":"yedi yüz elli beş","777":"yedi yüz yetmiş yedi","143":"yüz kırk üç","464":"dört yüz altmış dört","6":"altı","562":"beş yüz altmış iki","183":"yüz seksen üç","497":"dört yüz doksan yedi","518":"beş yüz on sekiz","362":"üç yüz altmış iki","439":"dört yüz otuz dokuz","169":"yüz altmış dokuz","411":"dört yüz on bir","705":"yedi yüz beş","478":"dört yüz yetmiş sekiz","384":"üç yüz seksen dört","398":"üç yüz doksan sekiz","836":"sekiz yüz otuz altı","955":"dokuz yüz elli beş","942":"dokuz yüz kırk iki","407":"dört yüz yedi","18":"on sekiz","912":"dokuz yüz on iki","376":"üç yüz yetmiş altı","785":"yedi yüz seksen beş","599":"beş yüz doksan dokuz","587":"beş yüz seksen yedi","609":"altı yüz dokuz","190":"yüz doksan","298":"iki yüz doksan sekiz","95":"doksan beş","923":"dokuz yüz yirmi üç","822":"sekiz yüz yirmi iki","601":"altı yüz bir","243":"iki yüz kırk üç","231":"iki yüz otuz bir","779":"yedi yüz yetmiş dokuz","551":"beş yüz elli bir","148":"yüz kırk sekiz","343":"üç yüz kırk üç","504":"beş yüz dört","753":"yedi yüz elli üç","981":"dokuz yüz seksen bir","697":"altı yüz doksan yedi","726":"yedi yüz yirmi altı","857":"sekiz yüz elli yedi","106":"bir yüz altı","707":"yedi yüz yedi","964":"dokuz yüz altmış dört","157":"yüz elli yedi","65":"altmış beş","935":"dokuz yüz otuz beş","203":"iki yüz üç","261":"iki yüz altmış bir","81":"seksen bir","321":"üç yüz yirmi bir","792":"yedi yüz doksan iki","86":"seksen altı","624":"altı yüz yirmi dört","371":"üç yüz yetmiş bir","656":"altı yüz elli altı","204":"iki yüz dört","435":"dört yüz otuz beş","814":"sekiz yüz on dört","924":"dokuz yüz yirmi dört","885":"sekiz yüz seksen beş","884":"sekiz yüz seksen dört","339":"üç yüz otuz dokuz","228":"iki yüz yirmi sekiz","760":"yedi yüz altmış","863":"sekiz yüz altmış üç","749":"yedi yüz kırk dokuz","268":"iki yüz altmış sekiz","531":"beş yüz otuz bir","829":"sekiz yüz yirmi dokuz","345":"üç yüz kırk beş","172":"yüz yetmiş iki","596":"beş yüz doksan altı","223":"iki yüz yirmi üç","613":"altı yüz on üç","721":"yedi yüz yirmi bir","282":"iki yüz seksen iki","669":"altı yüz altmış dokuz","420":"dört yüz yirmi","121":"yüz yirmi bir","952":"dokuz yüz elli iki","639":"altı yüz otuz dokuz","989":"dokuz yüz seksen dokuz","487":"dört yüz seksen yedi","494":"dört yüz doksan dört","238":"iki yüz otuz sekiz","873":"sekiz yüz yetmiş üç","577":"beş yüz yetmiş yedi","253":"iki yüz elli üç","448":"dört yüz kırk sekiz","216":"iki yüz on altı","852":"sekiz yüz elli iki","643":"altı yüz kırk üç","63":"altmış üç","179":"yüz yetmiş dokuz","713":"yedi yüz on üç","676":"altı yüz yetmiş altı","277":"iki yüz yetmiş yedi","938":"dokuz yüz otuz sekiz","879":"sekiz yüz yetmiş dokuz","929":"dokuz yüz yirmi dokuz","133":"yüz otuz üç","123":"yüz yirmi üç","304":"üç yüz dört","547":"beş yüz kırk yedi","631":"altı yüz otuz bir","258":"iki yüz elli sekiz","396":"üç yüz doksan altı","482":"dört yüz seksen iki","949":"dokuz yüz kırk dokuz","56":"elli altı","499":"dört yüz doksan dokuz","54":"elli dört","306":"üç yüz altı","70":"yetmiş","839":"sekiz yüz otuz dokuz","166":"yüz altmış altı","88":"seksen sekiz","30":"otuz","141":"yüz kırk bir","909":"dokuz yüz dokuz","403":"dört yüz üç","466":"dört yüz altmış altı","75":"yetmiş beş","134":"yüz otuz dört","618":"altı yüz on sekiz","848":"sekiz yüz kırk sekiz","450":"dört yüz elli","703":"yedi yüz üç","900":"dokuz yüz","318":"üç yüz on sekiz","972":"dokuz yüz yetmiş iki","473":"dört yüz yetmiş üç","3":"üç","185":"yüz seksen beş","248":"iki yüz kırk sekiz","146":"yüz kırk altı","802":"sekiz yüz iki","356":"üç yüz elli altı","4":"dört","528":"beş yüz yirmi sekiz","164":"yüz altmış dört","807":"sekiz yüz yedi"}